matplobbot_shared-0.1.82.dist-info/licenses/LICENSE
shared_lib/__init__.py
shared_lib/celery_app.py
shared_lib/constants.py
shared_lib/database.py
shared_lib/i18n.py
shared_lib/models.py
shared_lib/redis_client.py
shared_lib/schemas.py
shared_lib/tasks.py
shared_lib/locales/en.json
shared_lib/locales/ru.json
shared_lib/services/__init__.py
shared_lib/services/schedule_service.py
shared_lib/services/semantic_search.py
shared_lib/services/university_api.py
matplobbot_shared-0.1.82.dist-info/METADATA
matplobbot_shared-0.1.82.dist-info/WHEEL
matplobbot_shared-0.1.82.dist-info/top_level.txt
matplobbot_shared-0.1.82.dist-info/RECORD
