Metadata-Version: 2.4
Name: matplobbot-shared
Version: 0.1.82
Summary: Shared library for the Matplobbot ecosystem.
Author: Ackrome
Author-email: ivansergeyevich@gmail.com
Requires-Python: >=3.11
License-File: LICENSE
Requires-Dist: asyncpg
Requires-Dist: aiohttp
Requires-Dist: certifi
Requires-Dist: redis
Requires-Dist: cachetools
Requires-Dist: celery
Requires-Dist: Pillow
Requires-Dist: markdown-it-py
Requires-Dist: mdit-py-plugins
Dynamic: author
Dynamic: author-email
Dynamic: license-file
Dynamic: requires-dist
Dynamic: requires-python
Dynamic: summary
